{"country_name":"Grèce","country_value":"gr","city":[{"city_name":"Acharnes","city_value":"265488"},{"city_name":"Agia Paraskevi","city_value":"264194"},{"city_name":"Agia Varvara","city_value":"264111"},{"city_name":"Agrinio","city_value":"265560"},{"city_name":"Aigaleo","city_value":"265533"},{"city_name":"Aigio","city_value":"265500"},{"city_name":"Alexandroupoli","city_value":"736928"},{"city_name":"Alimos","city_value":"261614"},{"city_name":"Alimos","city_value":"6639653"},{"city_name":"Amaliada","city_value":"265252"},{"city_name":"Ano Liosia","city_value":"264888"},{"city_name":"Argos","city_value":"264670"},{"city_name":"Arta","city_value":"264559"},{"city_name":"Aspropyrgos","city_value":"264445"},{"city_name":"Athens","city_value":"264371"},{"city_name":"Chalkida","city_value":"260133"},{"city_name":"Chania","city_value":"260114"},{"city_name":"Chios","city_value":"259973"},{"city_name":"Cholargos","city_value":"259949"},{"city_name":"Drama","city_value":"736364"},{"city_name":"Edessa","city_value":"736357"},{"city_name":"Elefsina","city_value":"262752"},{"city_name":"Elliniko","city_value":"262719"},{"city_name":"Florina","city_value":"736229"},{"city_name":"Galatsi","city_value":"262135"},{"city_name":"Giannitsa","city_value":"733776"},{"city_name":"Ilion","city_value":"256601"},{"city_name":"Ioannina","city_value":"261779"},{"city_name":"Irakleio","city_value":"261743"},{"city_name":"Irakleion","city_value":"261745"},{"city_name":"Kaisariani","city_value":"261678"},{"city_name":"Kalamaria","city_value":"736083"},{"city_name":"Kalamata","city_value":"261604"},{"city_name":"Kallithea","city_value":"261414"},{"city_name":"Karditsa","city_value":"260989"},{"city_name":"Katerini","city_value":"735914"},{"city_name":"Kavala","city_value":"735861"},{"city_name":"Keratsini","city_value":"260204"},{"city_name":"Kerkyra","city_value":"2463679"},{"city_name":"Khalandrion","city_value":"260172"},{"city_name":"Kifisia","city_value":"259824"},{"city_name":"Kilkis","city_value":"735736"},{"city_name":"Komotini","city_value":"735640"},{"city_name":"Korinthos","city_value":"259289"},{"city_name":"Koropi","city_value":"259251"},{"city_name":"Kos","city_value":"259245"},{"city_name":"Kozani","city_value":"735563"},{"city_name":"Lamia","city_value":"258620"},{"city_name":"Larisa","city_value":"258576"},{"city_name":"Livadeia","city_value":"258463"},{"city_name":"Marousi","city_value":"265243"},{"city_name":"Marousi","city_value":"7522530"},{"city_name":"Megara","city_value":"257365"},{"city_name":"Melissia","city_value":"257302"},{"city_name":"Menemeni","city_value":"735215"},{"city_name":"Mesolongi","city_value":"6693122"},{"city_name":"Moskhaton","city_value":"256750"},{"city_name":"Mytilini","city_value":"256866"},{"city_name":"Nafpaktos","city_value":"256639"},{"city_name":"Naousa","city_value":"735030"},{"city_name":"Nea Erythraia","city_value":"256622"},{"city_name":"Nea Filadelfeia","city_value":"256621"},{"city_name":"Nea Ionia","city_value":"256614"},{"city_name":"Nea Smyrni","city_value":"256575"},{"city_name":"Nikaia","city_value":"256429"},{"city_name":"Oraiokastro","city_value":"734883"},{"city_name":"Orestiada","city_value":"734880"},{"city_name":"Palaio Faliro","city_value":"256075"},{"city_name":"Panorama","city_value":"734771"},{"city_name":"Patra","city_value":"255683"},{"city_name":"Peraia","city_value":"734712"},{"city_name":"Perama","city_value":"255588"},{"city_name":"Peristeri","city_value":"255524"},{"city_name":"Petroupolis","city_value":"255377"},{"city_name":"Piraeus","city_value":"255274"},{"city_name":"Polichni","city_value":"734538"},{"city_name":"Preveza","city_value":"254698"},{"city_name":"Ptolemaida","city_value":"734426"},{"city_name":"Pylaia","city_value":"734643"},{"city_name":"Pyrgos","city_value":"255229"},{"city_name":"Rethymno","city_value":"254352"},{"city_name":"Rodos","city_value":"400666"},{"city_name":"Salamis","city_value":"254144"},{"city_name":"Serres","city_value":"734330"},{"city_name":"Sparti","city_value":"253394"},{"city_name":"Sykies","city_value":"734301"},{"city_name":"Thessaloniki","city_value":"734077"},{"city_name":"Thivai","city_value":"252910"},{"city_name":"Trikala","city_value":"252664"},{"city_name":"Tripoli","city_value":"252601"},{"city_name":"Veroia","city_value":"733905"},{"city_name":"Volos","city_value":"251833"},{"city_name":"Voula","city_value":"251780"},{"city_name":"Vrilissia","city_value":"6324534"},{"city_name":"Vyronas","city_value":"251948"},{"city_name":"Xanthi","city_value":"733840"}]}